AUTHORS.rst
CONTRIBUTING.rst
HISTORY.rst
LICENSE
MANIFEST.in
README.rst
setup.cfg
setup.py
docs/Makefile
docs/authors.rst
docs/conf.py
docs/contributing.rst
docs/history.rst
docs/index.rst
docs/installation.rst
docs/make.bat
docs/readme.rst
docs/usage.rst
pyehik/__init__.py
pyehik/cli.py
pyehik/pyehik.py
pyehik/sdk.py
pyehik.egg-info/PKG-INFO
pyehik.egg-info/SOURCES.txt
pyehik.egg-info/dependency_links.txt
pyehik.egg-info/entry_points.txt
pyehik.egg-info/not-zip-safe
pyehik.egg-info/requires.txt
pyehik.egg-info/top_level.txt
tests/__init__.py
tests/test_pyehik.py