Metadata-Version: 1.1
Name: pyehik
Version: 0.1.5
Summary: Python binding hikvision sdk
Home-page: https://efossils.somxslibres.net/fossil/user/bit4bit/repository/pyehik/index
Author: Jovany Leandro G.C
Author-email: bit4bit@riseup.net
License: MIT license
Keywords: pyehik
Platform: UNKNOWN
Classifier: Development Status :: 2 - Pre-Alpha
Classifier: Intended Audience :: Developers
Classifier: License :: OSI Approved :: MIT License
Classifier: Natural Language :: English
Classifier: Programming Language :: Python :: 2
Classifier: Programming Language :: Python :: 2.7
Classifier: Programming Language :: Python :: 3
Classifier: Programming Language :: Python :: 3.4
Classifier: Programming Language :: Python :: 3.5
Classifier: Programming Language :: Python :: 3.6
Classifier: Programming Language :: Python :: 3.7
